flask_picocms
