Metadata-Version: 1.1
Name: Flask-PicoCMS
Version: 0.0.3
Summary: Lightweight CMS backend for Flask apps
Home-page: https://github.com/johnwilson/picocms
Author: John K.E. Wilson
Author-email: wilsonfiifi@gmail.com
License: MIT
Download-URL: https://github.com/johnwilson/picocms/archive/v0.0.3.tar.gz
Keywords: flask,cms
Platform: any
Classifier: Environment :: Web Environment
Classifier: Intended Audience :: Developers
Classifier: License :: OSI Approved :: MIT License
Classifier: Operating System :: OS Independent
Classifier: Programming Language :: Python
Classifier: Programming Language :: Python :: 2
Classifier: Programming Language :: Python :: 3
Classifier: Topic :: Internet :: WWW/HTTP :: Dynamic Content
Classifier: Topic :: Software Development :: Libraries :: Python Modules
